<?xml version="1.0" encoding="UTF-8" standalone="yes"?>
<ns2:profileDAO xmlns:ns2="Database">
    <profileList>
        <profile>
            <email>k</email>
            <username>k</username>
            <password>k</password>
            <first>k</first>
            <last>k</last>
            <listOfWatchLists/>
        </profile>
        <profile>
            <email>a</email>
            <username>a</username>
            <password>a</password>
            <first>a</first>
            <last>a</last>
            <listOfWatchLists>
                <watchListName>
                    <name>test1</name>
                    <dateCreated>2020-11-23T11:11:21.115-06:00</dateCreated>
                    <stockList/>
                </watchListName>
            </listOfWatchLists>
        </profile>
        <profile>
            <email>q</email>
            <username>q</username>
            <password>q</password>
            <first>q</first>
            <last>q</last>
            <listOfWatchLists>
                <watchListName>
                    <name>test1</name>
                    <dateCreated>2020-11-23T12:21:36.449-06:00</dateCreated>
                    <stockList/>
                </watchListName>
                <watchListName>
                    <name>test2</name>
                    <dateCreated>2020-11-23T12:21:44.220-06:00</dateCreated>
                    <stockList/>
                </watchListName>
                <watchListName>
                    <name>test3</name>
                    <dateCreated>2020-11-23T12:39:29.360-06:00</dateCreated>
                    <stockList/>
                </watchListName>
            </listOfWatchLists>
        </profile>
    </profileList>
</ns2:profileDAO>
